{
  "published": [
    {
      "account": "pros_peridade_do_reino",
      "video": "corte_00003.mp4",
      "platform": "youtube",
      "postId": "RXNj6xxrCak",
      "postUrl": "https://www.youtube.com/watch?v=RXNj6xxrCak",
      "via": "upload-post",
      "publishedAt": "2026-04-22T11:11:14.014Z"
    },
    {
      "account": "orar_prosperar",
      "video": "corte_00001.mp4",
      "platform": "youtube",
      "postId": "843529942f134c158e113d6d2f08862c",
      "success": true,
      "publishedAt": "2026-04-22T11:25:32.924Z"
    }
  ]
}