{
  "youtube_title": "Melhore Suas Finanças com Análise de Dados: Guia Prático",
  "youtube_description": "Aprenda a usar análise de dados para otimizar suas finanças pessoais. Dicas práticas e exemplos reais para empreendedoras brasileiras. #finanças #dados",
  "tags": [
    "finanças pessoais",
    "análise de dados",
    "empreendedorismo",
    "inteligência artificial",
    "educação financeira"
  ],
  "article_url": "https://wp.marinaveauvy.com.br",
  "source": "youtube-factory",
  "generatedAt": "2026-03-30T11:12:54.450Z"
}